wearpipe/__init__.py
wearpipe/wearpipe.py
wearpipe-0.0.3.dist-info/LICENSE.txt
wearpipe-0.0.3.dist-info/METADATA
wearpipe-0.0.3.dist-info/WHEEL
wearpipe-0.0.3.dist-info/top_level.txt
wearpipe-0.0.3.dist-info/RECORD
